dekit/__init__.py
dekit/deprecated.py
dekit/run_once.py
dekit-0.0.2.dist-info/LICENSE
dekit-0.0.2.dist-info/METADATA
dekit-0.0.2.dist-info/WHEEL
dekit-0.0.2.dist-info/top_level.txt
dekit-0.0.2.dist-info/RECORD
