Metadata-Version: 2.1
Name: dekit
Version: 0.0.2
Summary: A collection of useful Python decorators
Home-page: https://github.com/algobot76/dekit
Author: Kaitian Xie
Author-email: xkaitian@gmail.com
License: MIT
Platform: UNKNOWN
